beapy/__init__.py
beapy/bea_requests.py
beapy/bea_responses.py
beapy/core.py
beapy/formats.py
beapy/key.py
beapy/crosswalk/__init__.py
beapy/crosswalk/datasets.json
beapy/crosswalk/fixedassets.json
beapy/crosswalk/nipa.json
beapy/crosswalk/niunderlyingdetail.json
beapy/crosswalk/walker.py
beapy-0.2.4.dist-info/METADATA
beapy-0.2.4.dist-info/WHEEL
beapy-0.2.4.dist-info/top_level.txt
beapy-0.2.4.dist-info/RECORD
