Metadata-Version: 2.1
Name: beapy
Version: 0.2.4
Summary: A pandas-based python package for requesting data from the U.S. Bureau of Economic Analysis
Home-page: https://www.github.com/hotzsauce/bea-dev
Author: hotzsauce
Author-email: githotz@gmail.com
License: MIT
Keywords: economics,bea,bureau of economic analysis,nipa
Platform: UNKNOWN
Classifier: Development Status :: 3 - Alpha
Classifier: License :: OSI Approved :: MIT License
Classifier: Programming Language :: Python :: 3
Classifier: Programming Language :: Python :: 3.7
